setup.py
django_localcrawler.egg-info/PKG-INFO
django_localcrawler.egg-info/SOURCES.txt
django_localcrawler.egg-info/dependency_links.txt
django_localcrawler.egg-info/not-zip-safe
django_localcrawler.egg-info/requires.txt
django_localcrawler.egg-info/top_level.txt
localcrawler/__init__.py
localcrawler/core.py
localcrawler/models.py
localcrawler/settings.py
localcrawler/tests.py
localcrawler/management/__init__.py
localcrawler/management/commands/__init__.py
localcrawler/management/commands/localcrawler.py
testapp/__init__.py
testapp/manage.py
testapp/models.py
testapp/settings.py
testapp/tests.py
testapp/urls.py
testapp/views.py