Metadata-Version: 1.0
Name: django-localcrawler
Version: 0.1.1
Summary: django-localcrawler
Home-page: http://github.com/ojii/django-localcrawler
Author: Jonas Obrist
Author-email: jonas.obrist@divio.ch
License: BSD
Keywords: testing,django
Platform: UNKNOWN
Classifier: Programming Language :: Python
Classifier: Topic :: Software Development :: Libraries :: Python Modules
Classifier: Framework :: Django
Classifier: Environment :: Web Environment
